pdfsyntax/__init__.py
pdfsyntax/__main__.py
pdfsyntax/api.py
pdfsyntax/cli.py
pdfsyntax/display.py
pdfsyntax/docstruct.py
pdfsyntax/filestruct.py
pdfsyntax/filters.py
pdfsyntax/graphics.py
pdfsyntax/layout.py
pdfsyntax/markdown.py
pdfsyntax/objects.py
pdfsyntax/text.py
pdfsyntax-0.1.6.dist-info/licenses/LICENSE
pdfsyntax-0.1.6.dist-info/METADATA
pdfsyntax-0.1.6.dist-info/WHEEL
pdfsyntax-0.1.6.dist-info/entry_points.txt
pdfsyntax-0.1.6.dist-info/top_level.txt
pdfsyntax-0.1.6.dist-info/RECORD
