Metadata-Version: 2.4
Name: pdfsyntax
Version: 0.1.6
Summary: A Python library to inspect and modify the internal structure of a PDF file
Author-email: "Martin D." <desgeeko@gmail.com>
License: MIT license
Project-URL: Homepage, https://github.com/desgeeko/pdfsyntax
Project-URL: Bug Tracker, https://github.com/desgeeko/pdfsyntax/issues
Classifier: Programming Language :: Python :: 3
Classifier: License :: OSI Approved :: MIT License
Classifier: Operating System :: OS Independent
Classifier: Development Status :: 4 - Beta
Classifier: Intended Audience :: Developers
Classifier: Topic :: Software Development :: Libraries
Classifier: Topic :: Utilities
Requires-Python: >=3.8
License-File: LICENSE
Dynamic: license-file
